var jugueiros = {
"type": "FeatureCollection",
"name": "jugueiros",
"crs": { "type": "name", "properties": { "name": "urn:ogc:def:crs:OGC:1.3:CRS84" } },
"features": [
{ "type": "Feature", "properties": { "OID_": 0, "Name": "Associação Cultural e Recreativa de Jugueiros", "FolderPath": "Clubes_Felgueiras.kml\/Os Meus locais", "Tipologia": "Sem Relvado", "Lotacao": "Sem Bancada" }, "geometry": { "type": "Point", "coordinates": [ -8.221825009999975, 41.403080315000068, 0.0 ] } }
]
}
