var varziela = {
"type": "FeatureCollection",
"name": "varziela",
"crs": { "type": "name", "properties": { "name": "urn:ogc:def:crs:OGC:1.3:CRS84" } },
"features": [
{ "type": "Feature", "properties": { "OID_": 0, "Name": "Centro Recreativo Cultural e Desportivo de Varziela 1982", "FolderPath": "Clubes_Felgueiras.kml\/Os Meus locais", "Tipologia": "Sem Relvado", "Lotacao": "Sem Bancada" }, "geometry": { "type": "Point", "coordinates": [ -8.209157926999978, 41.345922841000061, 0.0 ] } }
]
}
